eia/__init__.py
eia/models/__init__.py
eia/models/example.py
eia/package/__extensions__.py
eia/package/__init__.py
eia/package/eia.py
eia/package/extension_map.json
eia/package/module_map.json
eia/provider.py
eia/router.py
eia/utils/__init__.py
eia/utils/helpers.py
openbb_eia-1.0.0.dist-info/entry_points.txt
openbb_eia-1.0.0.dist-info/METADATA
openbb_eia-1.0.0.dist-info/WHEEL
openbb_eia-1.0.0.dist-info/RECORD
