Metadata-Version: 2.1
Name: openbb-eia
Version: 1.0.0
Summary: 
Author: caique
Author-email: caique.cober.souza@gmail.com
Requires-Python: >=3.8.1,<3.12
Classifier: Programming Language :: Python :: 3
Classifier: Programming Language :: Python :: 3.9
Classifier: Programming Language :: Python :: 3.10
Classifier: Programming Language :: Python :: 3.11
Requires-Dist: openbb-core (>=1.1.0,<2.0.0)
Requires-Dist: openbb-devtools (>=1.0.0b1,<2.0.0)
